pyeodhistorical/__init__.py
pyeodhistorical/api.py
pyeodhistorical-0.0.1.dist-info/LICENSE
pyeodhistorical-0.0.1.dist-info/METADATA
pyeodhistorical-0.0.1.dist-info/WHEEL
pyeodhistorical-0.0.1.dist-info/top_level.txt
pyeodhistorical-0.0.1.dist-info/RECORD
